Metadata-Version: 1.0
Name: NumberGame
Version: 0.0.1
Summary: a simple game where you guess the CPUs random number
Home-page: UNKNOWN
Author: UNKNOWN
Author-email: UNKNOWN
License: UNKNOWN
Platform: UNKNOWN
